{
  "$schema": "https://raw.githubusercontent.com/spdx/spdx-spec/v2.2.1/schemas/spdx-schema.json",
  "spdxVersion": "SPDX-2.2",
  "dataLicense": "CC0-1.0",
  "SPDXID": "SPDXRef-DOCUMENT",
  "documentNamespace": "https://spdx.org/spdxdocs/opus-x86-windows-static-1.3.1#8-c8e84388-1e81-4205-ae7a-38ef69fa67b3",
  "name": "opus:x86-windows-static@1.3.1#8 396cb10612fd5ff65932cb51477a2861461c511113b2d2289adea8622405c6fc",
  "creationInfo": {
    "creators": [
      "Tool: vcpkg-67e17c1782801cf481be9ac0b3765dff3e4bdeb8"
    ],
    "created": "2023-03-28T03:25:10Z"
  },
  "relationships": [
    {
      "spdxElementId": "SPDXRef-port",
      "relationshipType": "GENERATES",
      "relatedSpdxElement": "SPDXRef-binary"
    },
    {
      "spdxElementId": "SPDXRef-port",
      "relationshipType": "CONTAINS",
      "relatedSpdxElement": "SPDXRef-file-0"
    },
    {
      "spdxElementId": "SPDXRef-port",
      "relationshipType": "CONTAINS",
      "relatedSpdxElement": "SPDXRef-file-1"
    },
    {
      "spdxElementId": "SPDXRef-port",
      "relationshipType": "CONTAINS",
      "relatedSpdxElement": "SPDXRef-file-2"
    },
    {
      "spdxElementId": "SPDXRef-binary",
      "relationshipType": "GENERATED_FROM",
      "relatedSpdxElement": "SPDXRef-port"
    },
    {
      "spdxElementId": "SPDXRef-file-0",
      "relationshipType": "CONTAINED_BY",
      "relatedSpdxElement": "SPDXRef-port"
    },
    {
      "spdxElementId": "SPDXRef-file-1",
      "relationshipType": "CONTAINED_BY",
      "relatedSpdxElement": "SPDXRef-port"
    },
    {
      "spdxElementId": "SPDXRef-file-2",
      "relationshipType": "CONTAINED_BY",
      "relatedSpdxElement": "SPDXRef-port"
    },
    {
      "spdxElementId": "SPDXRef-file-2",
      "relationshipType": "DEPENDENCY_MANIFEST_OF",
      "relatedSpdxElement": "SPDXRef-port"
    }
  ],
  "packages": [
    {
      "name": "opus",
      "SPDXID": "SPDXRef-port",
      "versionInfo": "1.3.1#8",
      "downloadLocation": "git+https://github.com/Microsoft/vcpkg#ports/opus",
      "homepage": "https://github.com/xiph/opus",
      "licenseConcluded": "BSD-3-Clause",
      "licenseDeclared": "NOASSERTION",
      "copyrightText": "NOASSERTION",
      "description": "Totally open, royalty-free, highly versatile audio codec",
      "comment": "This is the port (recipe) consumed by vcpkg."
    },
    {
      "name": "opus:x86-windows-static",
      "SPDXID": "SPDXRef-binary",
      "versionInfo": "396cb10612fd5ff65932cb51477a2861461c511113b2d2289adea8622405c6fc",
      "downloadLocation": "NONE",
      "licenseConcluded": "BSD-3-Clause",
      "licenseDeclared": "NOASSERTION",
      "copyrightText": "NOASSERTION",
      "comment": "This is a binary package built by vcpkg."
    },
    {
      "SPDXID": "SPDXRef-resource-1",
      "name": "xiph/opus",
      "downloadLocation": "git+https://github.com/xiph/opus@5c94ec3205c30171ffd01056f5b4622b7c0ab54c",
      "licenseConcluded": "NOASSERTION",
      "licenseDeclared": "NOASSERTION",
      "copyrightText": "NOASSERTION",
      "checksums": [
        {
          "algorithm": "SHA512",
          "checksumValue": "2423b1fc86d5b46c32d8e3bde5fc2b410a5c25c001995ce234a94a3a6c7a8b1446fdf19eafe9d6a8a7356fe0857697053db5eb8380d18f8111818aa770b4c4ea"
        }
      ]
    }
  ],
  "files": [
    {
      "fileName": "./fix-pkgconfig-version.patch",
      "SPDXID": "SPDXRef-file-0",
      "checksums": [
        {
          "algorithm": "SHA256",
          "checksumValue": "013447bc63b0a8e14a8c2f0db3537f2cf0b99b3b81a3a43a482ca3268f7cc249"
        }
      ],
      "licenseConcluded": "NOASSERTION",
      "copyrightText": "NOASSERTION"
    },
    {
      "fileName": "./portfile.cmake",
      "SPDXID": "SPDXRef-file-1",
      "checksums": [
        {
          "algorithm": "SHA256",
          "checksumValue": "1a2f37d46bab59c9d7e9af44fc31d8bf965d2af6dc36a209e0cf26607c69c9ca"
        }
      ],
      "licenseConcluded": "NOASSERTION",
      "copyrightText": "NOASSERTION"
    },
    {
      "fileName": "./vcpkg.json",
      "SPDXID": "SPDXRef-file-2",
      "checksums": [
        {
          "algorithm": "SHA256",
          "checksumValue": "6cd523f3996a46825bacbfbec7507c020458ee1e3939007913027285e80a603d"
        }
      ],
      "licenseConcluded": "NOASSERTION",
      "copyrightText": "NOASSERTION"
    }
  ]
}
