{
  "$schema": "https://raw.githubusercontent.com/spdx/spdx-spec/v2.2.1/schemas/spdx-schema.json",
  "spdxVersion": "SPDX-2.2",
  "dataLicense": "CC0-1.0",
  "SPDXID": "SPDXRef-DOCUMENT",
  "documentNamespace": "https://spdx.org/spdxdocs/libvpx-arm64-ios-1.12.0-21592a2a-3fa3-4071-99b3-616a5f19bd6f",
  "name": "libvpx:arm64-ios@1.12.0 6743faf2eb859e0e4b021fe73cfa01ea38732721db07bb9bf381db28ebace9ea",
  "creationInfo": {
    "creators": [
      "Tool: vcpkg-bedcba5172f5e4b91caac660ab7afe92c27a9895"
    ],
    "created": "2023-04-16T14:48:22Z"
  },
  "relationships": [
    {
      "spdxElementId": "SPDXRef-port",
      "relationshipType": "GENERATES",
      "relatedSpdxElement": "SPDXRef-binary"
    },
    {
      "spdxElementId": "SPDXRef-port",
      "relationshipType": "CONTAINS",
      "relatedSpdxElement": "SPDXRef-file-0"
    },
    {
      "spdxElementId": "SPDXRef-port",
      "relationshipType": "CONTAINS",
      "relatedSpdxElement": "SPDXRef-file-1"
    },
    {
      "spdxElementId": "SPDXRef-port",
      "relationshipType": "CONTAINS",
      "relatedSpdxElement": "SPDXRef-file-2"
    },
    {
      "spdxElementId": "SPDXRef-port",
      "relationshipType": "CONTAINS",
      "relatedSpdxElement": "SPDXRef-file-3"
    },
    {
      "spdxElementId": "SPDXRef-port",
      "relationshipType": "CONTAINS",
      "relatedSpdxElement": "SPDXRef-file-4"
    },
    {
      "spdxElementId": "SPDXRef-port",
      "relationshipType": "CONTAINS",
      "relatedSpdxElement": "SPDXRef-file-5"
    },
    {
      "spdxElementId": "SPDXRef-port",
      "relationshipType": "CONTAINS",
      "relatedSpdxElement": "SPDXRef-file-6"
    },
    {
      "spdxElementId": "SPDXRef-binary",
      "relationshipType": "GENERATED_FROM",
      "relatedSpdxElement": "SPDXRef-port"
    },
    {
      "spdxElementId": "SPDXRef-file-0",
      "relationshipType": "CONTAINED_BY",
      "relatedSpdxElement": "SPDXRef-port"
    },
    {
      "spdxElementId": "SPDXRef-file-1",
      "relationshipType": "CONTAINED_BY",
      "relatedSpdxElement": "SPDXRef-port"
    },
    {
      "spdxElementId": "SPDXRef-file-2",
      "relationshipType": "CONTAINED_BY",
      "relatedSpdxElement": "SPDXRef-port"
    },
    {
      "spdxElementId": "SPDXRef-file-3",
      "relationshipType": "CONTAINED_BY",
      "relatedSpdxElement": "SPDXRef-port"
    },
    {
      "spdxElementId": "SPDXRef-file-3",
      "relationshipType": "DEPENDENCY_MANIFEST_OF",
      "relatedSpdxElement": "SPDXRef-port"
    },
    {
      "spdxElementId": "SPDXRef-file-4",
      "relationshipType": "CONTAINED_BY",
      "relatedSpdxElement": "SPDXRef-port"
    },
    {
      "spdxElementId": "SPDXRef-file-5",
      "relationshipType": "CONTAINED_BY",
      "relatedSpdxElement": "SPDXRef-port"
    },
    {
      "spdxElementId": "SPDXRef-file-6",
      "relationshipType": "CONTAINED_BY",
      "relatedSpdxElement": "SPDXRef-port"
    }
  ],
  "packages": [
    {
      "name": "libvpx",
      "SPDXID": "SPDXRef-port",
      "versionInfo": "1.12.0",
      "downloadLocation": "git+https://github.com/Microsoft/vcpkg#ports/libvpx",
      "homepage": "https://github.com/webmproject/libvpx",
      "licenseConcluded": "BSD-3-Clause",
      "licenseDeclared": "NOASSERTION",
      "copyrightText": "NOASSERTION",
      "description": "The reference software implementation for the video coding formats VP8 and VP9.",
      "comment": "This is the port (recipe) consumed by vcpkg."
    },
    {
      "name": "libvpx:arm64-ios",
      "SPDXID": "SPDXRef-binary",
      "versionInfo": "6743faf2eb859e0e4b021fe73cfa01ea38732721db07bb9bf381db28ebace9ea",
      "downloadLocation": "NONE",
      "licenseConcluded": "BSD-3-Clause",
      "licenseDeclared": "NOASSERTION",
      "copyrightText": "NOASSERTION",
      "comment": "This is a binary package built by vcpkg."
    },
    {
      "SPDXID": "SPDXRef-resource-1",
      "name": "webmproject/libvpx",
      "downloadLocation": "git+https://github.com/webmproject/libvpx@v${LIBVPX_VERSION}",
      "licenseConcluded": "NOASSERTION",
      "licenseDeclared": "NOASSERTION",
      "copyrightText": "NOASSERTION",
      "checksums": [
        {
          "algorithm": "SHA512",
          "checksumValue": "dc059bc3102b75524ae29989372334b3e0f2acf1520e5a4daa4073831bb55949d82897c498fb9d2d38b59f1a66bb0ad24407d0d086b1e3a8394a4933f04f2ed0"
        }
      ]
    }
  ],
  "files": [
    {
      "fileName": "./unofficial-libvpx-config.cmake.in",
      "SPDXID": "SPDXRef-file-0",
      "checksums": [
        {
          "algorithm": "SHA256",
          "checksumValue": "b2b224740b36b1a1c328e50ad2653f5d954601be791500aaf3cb20c432eeeb70"
        }
      ],
      "licenseConcluded": "NOASSERTION",
      "copyrightText": "NOASSERTION"
    },
    {
      "fileName": "./0004-remove-library-suffixes.patch",
      "SPDXID": "SPDXRef-file-1",
      "checksums": [
        {
          "algorithm": "SHA256",
          "checksumValue": "3a7edcb553b1191b48696fc5a56ad5a43ae0cedb658ca42ba07473fa32bbc209"
        }
      ],
      "licenseConcluded": "NOASSERTION",
      "copyrightText": "NOASSERTION"
    },
    {
      "fileName": "./portfile.cmake",
      "SPDXID": "SPDXRef-file-2",
      "checksums": [
        {
          "algorithm": "SHA256",
          "checksumValue": "b3c3f6d010ad028249d2a4f13579658af3b4fa953cc5a1fc19c720a26997a47d"
        }
      ],
      "licenseConcluded": "NOASSERTION",
      "copyrightText": "NOASSERTION"
    },
    {
      "fileName": "./vcpkg.json",
      "SPDXID": "SPDXRef-file-3",
      "checksums": [
        {
          "algorithm": "SHA256",
          "checksumValue": "1b892ef96a341d25113f9c696ef042241aa3e84138f4f10b9fc8b50b4dbfe3e8"
        }
      ],
      "licenseConcluded": "NOASSERTION",
      "copyrightText": "NOASSERTION"
    },
    {
      "fileName": "./0002-Fix-nasm-debug-format-flag.patch",
      "SPDXID": "SPDXRef-file-4",
      "checksums": [
        {
          "algorithm": "SHA256",
          "checksumValue": "e7f1549ae581324b3997c40678f9b4f1f0839c4584db0c525adad52c467d5551"
        }
      ],
      "licenseConcluded": "NOASSERTION",
      "copyrightText": "NOASSERTION"
    },
    {
      "fileName": "./vpx.pc.in",
      "SPDXID": "SPDXRef-file-5",
      "checksums": [
        {
          "algorithm": "SHA256",
          "checksumValue": "65aca7f9942b226614d11a9cfdac28cbb83cefac2e5a2e60f86fd7b11b4e8b47"
        }
      ],
      "licenseConcluded": "NOASSERTION",
      "copyrightText": "NOASSERTION"
    },
    {
      "fileName": "./0003-add-uwp-v142-and-v143-support.patch",
      "SPDXID": "SPDXRef-file-6",
      "checksums": [
        {
          "algorithm": "SHA256",
          "checksumValue": "1b3057d0d3cd186c4b44ee97a65f6f7a57d1db3f0e09ca87d01c1aee202df217"
        }
      ],
      "licenseConcluded": "NOASSERTION",
      "copyrightText": "NOASSERTION"
    }
  ]
}
